{
  "fearGreed": 31,
  "fearGreedClassification": "Fear",
  "btcDominance": 58.32,
  "altseasonIndex": 39,
  "fedWatch": {
    "currentRate": {
      "range": "4.25-4.50%",
      "midpoint": 4.375
    },
    "nextMeeting": {
      "date": "2026-07-29",
      "label": "28-29 Jul 2026",
      "time": "16:00",
      "daysUntil": 12
    },
    "probabilities": {
      "cut": 30,
      "hold": 60,
      "hike": 10
    },
    "lastDecision": "Corte 25pb"
  },
  "marketIndicators": {
    "vix": {
      "value": 18.46,
      "change": 0,
      "status": "elevated"
    },
    "dxy": {
      "value": 100.82,
      "change": 0
    },
    "gold": {
      "value": 3986.1,
      "change": 0
    },
    "sp500": {
      "value": 7533.77,
      "change": 0
    },
    "treasury10y": {
      "value": 4.525,
      "change": 0
    },
    "btcPrice": null,
    "ethPrice": null,
    "totalMarketCap": {
      "value": 2252788403868.055,
      "formatted": "$2.25T",
      "change": -1.3078463823481405
    }
  },
  "lastUpdate": "2026-07-17T12:46:52.662Z",
  "error": null
}