{
  "fearGreed": 38,
  "fearGreedClassification": "Fear",
  "btcDominance": 59.87,
  "altseasonIndex": 37,
  "fedWatch": {
    "currentRate": {
      "range": "4.25-4.50%",
      "midpoint": 4.375
    },
    "nextMeeting": {
      "date": "2026-06-17",
      "label": "16-17 Jun 2026",
      "time": "16:00",
      "daysUntil": 24
    },
    "probabilities": {
      "cut": 30,
      "hold": 60,
      "hike": 10
    },
    "lastDecision": "Corte 25pb"
  },
  "marketIndicators": {
    "vix": {
      "value": 16.7,
      "change": 0,
      "status": "normal"
    },
    "dxy": {
      "value": 99.32,
      "change": 0
    },
    "gold": {
      "value": 4523.2,
      "change": 0
    },
    "sp500": {
      "value": 7473.47,
      "change": 0
    },
    "treasury10y": {
      "value": 4.558,
      "change": 0
    },
    "btcPrice": null,
    "ethPrice": null,
    "totalMarketCap": {
      "value": 2647582288892.344,
      "formatted": "$2.65T",
      "change": 1.6761083424539456
    }
  },
  "lastUpdate": "2026-05-24T01:28:15.220Z",
  "error": null
}