{
  "fearGreed": 15,
  "fearGreedClassification": "Extreme fear",
  "btcDominance": 58.07,
  "altseasonIndex": 37,
  "fedWatch": {
    "currentRate": {
      "range": "4.25-4.50%",
      "midpoint": 4.375
    },
    "nextMeeting": {
      "date": "2026-03-18",
      "label": "17-18 Mar 2026",
      "time": "16:00",
      "daysUntil": 16
    },
    "probabilities": {
      "cut": 40,
      "hold": 55,
      "hike": 5
    },
    "lastDecision": "Corte 25pb"
  },
  "marketIndicators": {
    "vix": {
      "value": 19.86,
      "change": 0,
      "status": "elevated"
    },
    "dxy": {
      "value": 98.14,
      "change": 0
    },
    "gold": {
      "value": 5392.2,
      "change": 0
    },
    "sp500": {
      "value": 6878.88,
      "change": 0
    },
    "treasury10y": {
      "value": 3.962,
      "change": 0
    },
    "btcPrice": null,
    "ethPrice": null,
    "totalMarketCap": {
      "value": 2354254348268.599,
      "formatted": "$2.35T",
      "change": -1.3665746128986376
    }
  },
  "lastUpdate": "2026-03-02T06:32:20.020Z",
  "error": null
}