{
  "fearGreed": 39,
  "fearGreedClassification": "Fear",
  "btcDominance": 60.18,
  "altseasonIndex": 37,
  "fedWatch": {
    "currentRate": {
      "range": "4.25-4.50%",
      "midpoint": 4.375
    },
    "nextMeeting": {
      "date": "2026-06-17",
      "label": "16-17 Jun 2026",
      "time": "16:00",
      "daysUntil": 29
    },
    "probabilities": {
      "cut": 30,
      "hold": 60,
      "hike": 10
    },
    "lastDecision": "Corte 25pb"
  },
  "marketIndicators": {
    "vix": {
      "value": 17.8,
      "change": 0,
      "status": "normal"
    },
    "dxy": {
      "value": 99.27,
      "change": 0
    },
    "gold": {
      "value": 4510.4,
      "change": 0
    },
    "sp500": {
      "value": 7390.91,
      "change": 0
    },
    "treasury10y": {
      "value": 4.661,
      "change": 0
    },
    "btcPrice": null,
    "ethPrice": null,
    "totalMarketCap": {
      "value": 2644860534789.6133,
      "formatted": "$2.64T",
      "change": 0.3204070246671618
    }
  },
  "lastUpdate": "2026-05-19T17:16:40.143Z",
  "error": null
}