{
  "fearGreed": 15,
  "fearGreedClassification": "Extreme fear",
  "btcDominance": 58.57,
  "altseasonIndex": 36,
  "fedWatch": {
    "currentRate": {
      "range": "4.25-4.50%",
      "midpoint": 4.375
    },
    "nextMeeting": {
      "date": "2026-03-18",
      "label": "17-18 Mar 2026",
      "time": "16:00",
      "daysUntil": 16
    },
    "probabilities": {
      "cut": 40,
      "hold": 55,
      "hike": 5
    },
    "lastDecision": "Corte 25pb"
  },
  "marketIndicators": {
    "vix": {
      "value": 21.38,
      "change": 0,
      "status": "elevated"
    },
    "dxy": {
      "value": 98.55,
      "change": 0
    },
    "gold": {
      "value": 5356.1,
      "change": 0
    },
    "sp500": {
      "value": 6882.8,
      "change": 0
    },
    "treasury10y": {
      "value": 4.048,
      "change": 0
    },
    "btcPrice": null,
    "ethPrice": null,
    "totalMarketCap": {
      "value": 2445270653700.572,
      "formatted": "$2.45T",
      "change": 5.032305816550178
    }
  },
  "lastUpdate": "2026-03-02T20:55:00.112Z",
  "error": null
}